{
  "last_updated": "2026-01-01T20:20:16.526856Z",
  "total_movies": 21,
  "movies": [
    {
      "episode_number": null,
      "episode_url": "https://maximumfun.org/episodes/friendly-fire/duck-soup-1933/",
      "title": "Duck Soup",
      "year": "1933",
      "imdb_id": "tt0023969",
      "imdb_rating": "7.7",
      "imdb_votes": "64,386",
      "imdb_url": "https://www.imdb.com/title/tt0023969",
      "runtime": "69 min",
      "genre": "Comedy, Musical",
      "director": "Leo McCarey",
      "plot": "Rufus T. Firefly is named the dictator of bankrupt Freedonia and declares war on neighboring Sylvania over the love of his wealthy backer Mrs. Teasdale, contending with two inept spies who can't seem to keep straight which side th...",
      "poster": "https://m.media-amazon.com/images/M/MV5BNGE5Mzg3NzMtZmI3My00ZWQwLThjYjYtOTZmZjQyNDVjMjIwXkEyXkFqcGc@._V1_SX300.jpg",
      "streaming_options": [
        {
          "service": "apple",
          "type": "rent",
          "quality": "hd",
          "link": "https://tv.apple.com/us/movie/duck-soup/umc.cmc.61cw5myr098h8fsd9dqxu9emx",
          "price": "USD3.99"
        },
        {
          "service": "apple",
          "type": "buy",
          "quality": "hd",
          "link": "https://tv.apple.com/us/movie/duck-soup/umc.cmc.61cw5myr098h8fsd9dqxu9emx",
          "price": "USD14.99"
        },
        {
          "service": "prime",
          "type": "subscription",
          "quality": "sd",
          "link": "https://www.amazon.com/gp/video/detail/B000N6OLB0/ref=atv_dp"
        },
        {
          "service": "prime",
          "type": "rent",
          "quality": "sd",
          "link": "https://www.amazon.com/gp/video/detail/B000N6OLB0/ref=atv_dp",
          "price": "USD3.79"
        },
        {
          "service": "prime",
          "type": "buy",
          "quality": "sd",
          "link": "https://www.amazon.com/gp/video/detail/B000N6OLB0/ref=atv_dp",
          "price": "USD14.99"
        }
      ]
    },
    {
      "episode_number": "155",
      "episode_url": "https://maximumfun.org/episodes/friendly-fire/operation-amsterdam-1959/",
      "title": "A Midnight Clear",
      "year": "1992",
      "imdb_id": "tt0102443",
      "imdb_rating": "7.1",
      "imdb_votes": "10,272",
      "imdb_url": "https://www.imdb.com/title/tt0102443",
      "runtime": "108 min",
      "genre": "Drama, War",
      "director": "Keith Gordon",
      "plot": "The Ardennes Forest, December 1944. A squad of six US infantrymen is sent to occupy a house to use as an observation post as the German Army is expected to advance through that area. However, the Germans seem oddly friendly.",
      "poster": "https://m.media-amazon.com/images/M/MV5BNTA4ZjRlYWUtODkxMy00YWJiLWIxNWItOTU2NGE2OGY2ZmZhXkEyXkFqcGc@._V1_SX300.jpg",
      "streaming_options": [
        {
          "service": "prime",
          "type": "addon",
          "quality": "sd",
          "link": "https://www.amazon.com/gp/video/detail/B084KSM3CP/ref=atv_dp"
        },
        {
          "service": "prime",
          "type": "rent",
          "quality": "hd",
          "link": "https://www.amazon.com/gp/video/detail/B084KSM3CP/ref=atv_dp",
          "price": "USD3.59"
        },
        {
          "service": "prime",
          "type": "rent",
          "quality": "sd",
          "link": "https://www.amazon.com/gp/video/detail/B084KSM3CP/ref=atv_dp",
          "price": "USD2.99"
        },
        {
          "service": "prime",
          "type": "buy",
          "quality": "sd",
          "link": "https://www.amazon.com/gp/video/detail/B084KSM3CP/ref=atv_dp",
          "price": "USD7.99"
        },
        {
          "service": "apple",
          "type": "buy",
          "quality": "hd",
          "link": "https://tv.apple.com/us/movie/a-midnight-clear/umc.cmc.1xryf6pcqja67wn8qxugxlkzc?playableId=tvs.sbd.9001%3A1528390347",
          "price": "USD9.99"
        },
        {
          "service": "apple",
          "type": "rent",
          "quality": "hd",
          "link": "https://tv.apple.com/us/movie/a-midnight-clear/umc.cmc.1xryf6pcqja67wn8qxugxlkzc?playableId=tvs.sbd.9001%3A1528390347",
          "price": "USD3.99"
        },
        {
          "service": "prime",
          "type": "buy",
          "quality": "hd",
          "link": "https://www.amazon.com/gp/video/detail/B084KSM3CP/ref=atv_dp",
          "price": "USD8.99"
        },
        {
          "service": "apple",
          "type": "buy",
          "quality": "sd",
          "link": "https://tv.apple.com/us/movie/a-midnight-clear/umc.cmc.1xryf6pcqja67wn8qxugxlkzc?playableId=tvs.sbd.9001%3A1528390347",
          "price": "USD7.99"
        },
        {
          "service": "tubi",
          "type": "free",
          "quality": "hd",
          "link": "https://tubitv.com/movies/548580/a-midnight-clear"
        },
        {
          "service": "plutotv",
          "type": "free",
          "quality": "sd",
          "link": "https://pluto.tv/gsa/on-demand/movies/5f5ad94b638b1800139e73bf/details"
        }
      ]
    },
    {
      "episode_number": "154",
      "episode_url": "https://maximumfun.org/episodes/friendly-fire/a-midnight-clear-1992/",
      "title": "Troy",
      "year": "2004",
      "imdb_id": "tt0332452",
      "imdb_rating": "7.3",
      "imdb_votes": "606,682",
      "imdb_url": "https://www.imdb.com/title/tt0332452",
      "runtime": "163 min",
      "genre": "Action, Adventure, Drama",
      "director": "Wolfgang Petersen",
      "plot": "An adaptation of Homer's great epic, the film follows the assault on Troy by the united Greek forces.",
      "poster": "https://m.media-amazon.com/images/M/MV5BMTk5MzU1MDMwMF5BMl5BanBnXkFtZTcwNjczODMzMw@@._V1_SX300.jpg",
      "streaming_options": [
        {
          "service": "apple",
          "type": "buy",
          "quality": "hd",
          "link": "https://tv.apple.com/us/movie/troy/umc.cmc.7bm2k5rpbstbpoqknatgrp9ct?playableId=tvs.sbd.9001%3A295210182",
          "price": "USD14.99"
        },
        {
          "service": "apple",
          "type": "rent",
          "quality": "hd",
          "link": "https://tv.apple.com/us/movie/troy/umc.cmc.7bm2k5rpbstbpoqknatgrp9ct?playableId=tvs.sbd.9001%3A295210182",
          "price": "USD3.99"
        },
        {
          "service": "peacock",
          "type": "subscription",
          "quality": "hd",
          "link": "https://www.peacocktv.com/watch/asset/movies/troy/c4b33c83-79a8-36af-ac18-39eaca790dcd"
        },
        {
          "service": "prime",
          "type": "addon",
          "quality": "sd",
          "link": "https://www.amazon.com/gp/video/detail/0N8VNX138FWG8S5AC7C58T1HY1/ref=atv_dp"
        },
        {
          "service": "prime",
          "type": "addon",
          "quality": "sd",
          "link": "https://www.amazon.com/gp/video/detail/0N8VNX138FWG8S5AC7C58T1HY1/ref=atv_dp"
        },
        {
          "service": "prime",
          "type": "buy",
          "quality": "hd",
          "link": "https://www.amazon.com/gp/video/detail/0N8VNX138FWG8S5AC7C58T1HY1/ref=atv_dp",
          "price": "USD7.99"
        },
        {
          "service": "prime",
          "type": "rent",
          "quality": "hd",
          "link": "https://www.amazon.com/gp/video/detail/0N8VNX138FWG8S5AC7C58T1HY1/ref=atv_dp",
          "price": "USD3.99"
        },
        {
          "service": "prime",
          "type": "buy",
          "quality": "hd",
          "link": "https://www.amazon.com/gp/video/detail/0OSAJSFX4B71U1B1PIMSUKLNFM/ref=atv_dp",
          "price": "USD14.99"
        }
      ]
    },
    {
      "episode_number": "153",
      "episode_url": "https://maximumfun.org/episodes/friendly-fire/attack-1956/",
      "title": "In the Army Now",
      "year": "1994",
      "imdb_id": "tt0110123",
      "imdb_rating": "4.9",
      "imdb_votes": "15,130",
      "imdb_url": "https://www.imdb.com/title/tt0110123",
      "runtime": "91 min",
      "genre": "Comedy, War",
      "director": "Daniel Petrie Jr.",
      "plot": "Two misguided youths join the reserves to make some money for their entrepreneurial dreams. No sooner than they finish basic training are they called up to do their part to save the free world.",
      "poster": "https://m.media-amazon.com/images/M/MV5BYjliOGJmOTAtNTQ1My00NzQ0LWE2MTMtOWYwOWM2NDU1YTU3XkEyXkFqcGc@._V1_SX300.jpg",
      "streaming_options": [
        {
          "service": "apple",
          "type": "buy",
          "quality": "sd",
          "link": "https://tv.apple.com/us/movie/in-the-army-now/umc.cmc.2h784afu9psem3m4xy2idrk2n?playableId=tvs.sbd.9001%3A443079148",
          "price": "USD17.99"
        },
        {
          "service": "apple",
          "type": "rent",
          "quality": "sd",
          "link": "https://tv.apple.com/us/movie/in-the-army-now/umc.cmc.2h784afu9psem3m4xy2idrk2n?playableId=tvs.sbd.9001%3A443079148",
          "price": "USD3.99"
        },
        {
          "service": "apple",
          "type": "buy",
          "quality": "hd",
          "link": "https://tv.apple.com/us/movie/in-the-army-now/umc.cmc.2h784afu9psem3m4xy2idrk2n?playableId=tvs.sbd.9001%3A443079148",
          "price": "USD17.99"
        },
        {
          "service": "apple",
          "type": "rent",
          "quality": "hd",
          "link": "https://tv.apple.com/us/movie/in-the-army-now/umc.cmc.2h784afu9psem3m4xy2idrk2n?playableId=tvs.sbd.9001%3A443079148",
          "price": "USD3.99"
        },
        {
          "service": "prime",
          "type": "rent",
          "quality": "hd",
          "link": "https://www.amazon.com/gp/video/detail/0JGM86S7LB5PGRHX7KVY8RGBFD/ref=atv_dp",
          "price": "USD3.79"
        },
        {
          "service": "prime",
          "type": "buy",
          "quality": "hd",
          "link": "https://www.amazon.com/gp/video/detail/0JGM86S7LB5PGRHX7KVY8RGBFD/ref=atv_dp",
          "price": "USD17.99"
        }
      ]
    },
    {
      "episode_number": "152",
      "episode_url": "https://maximumfun.org/episodes/friendly-fire/troy-2004-directors-cut/",
      "title": "Age of Heroes",
      "year": "2011",
      "imdb_id": "tt1590950",
      "imdb_rating": "5.5",
      "imdb_votes": "10,388",
      "imdb_url": "https://www.imdb.com/title/tt1590950",
      "runtime": "94 min",
      "genre": "Action, Adventure, Drama",
      "director": "Adrian Vitoria",
      "plot": "The true story of the formation of Ian Fleming's 30 Commando unit, a precursor for the elite forces in the U.K.",
      "poster": "https://m.media-amazon.com/images/M/MV5BMjE2MzQ1MDA1M15BMl5BanBnXkFtZTcwNjUzMjEyNQ@@._V1_SX300.jpg",
      "streaming_options": [
        {
          "service": "apple",
          "type": "buy",
          "quality": "hd",
          "link": "https://tv.apple.com/us/movie/age-of-heroes/umc.cmc.4o834zeetyn9v6yx2cnhtnu9s?playableId=tvs.sbd.9001%3A1610617175",
          "price": "USD9.99"
        },
        {
          "service": "apple",
          "type": "rent",
          "quality": "hd",
          "link": "https://tv.apple.com/us/movie/age-of-heroes/umc.cmc.4o834zeetyn9v6yx2cnhtnu9s?playableId=tvs.sbd.9001%3A1610617175",
          "price": "USD3.99"
        },
        {
          "service": "prime",
          "type": "subscription",
          "quality": "sd",
          "link": "https://www.amazon.com/gp/video/detail/B0073L8W6S/ref=atv_dp"
        },
        {
          "service": "prime",
          "type": "rent",
          "quality": "sd",
          "link": "https://www.amazon.com/gp/video/detail/B0073L8W6S/ref=atv_dp",
          "price": "USD1.99"
        },
        {
          "service": "prime",
          "type": "rent",
          "quality": "hd",
          "link": "https://www.amazon.com/gp/video/detail/B0073L8W6S/ref=atv_dp",
          "price": "USD2.99"
        },
        {
          "service": "prime",
          "type": "buy",
          "quality": "hd",
          "link": "https://www.amazon.com/gp/video/detail/B0073L8W6S/ref=atv_dp",
          "price": "USD9.99"
        },
        {
          "service": "tubi",
          "type": "free",
          "quality": "hd",
          "link": "https://tubitv.com/movies/100004296/age-of-heroes"
        }
      ]
    },
    {
      "episode_number": null,
      "episode_url": "https://maximumfun.org/boco/",
      "title": "Exodus",
      "year": "1960",
      "imdb_id": "tt0053804",
      "imdb_rating": "6.7",
      "imdb_votes": "12,136",
      "imdb_url": "https://www.imdb.com/title/tt0053804",
      "runtime": "208 min",
      "genre": "Action, Drama, War",
      "director": "Otto Preminger",
      "plot": "The State of Israel is created in 1948, resulting in war with its Arab neighbors.",
      "poster": "https://m.media-amazon.com/images/M/MV5BMTk4NjMxNjcyOV5BMl5BanBnXkFtZTgwNDAwNTIxMDE@._V1_SX300.jpg",
      "streaming_options": [
        {
          "service": "apple",
          "type": "rent",
          "quality": "hd",
          "link": "https://tv.apple.com/us/movie/exodus/umc.cmc.43m6x8i0l0noq5r30cpkgukix",
          "price": "USD3.99"
        },
        {
          "service": "apple",
          "type": "buy",
          "quality": "hd",
          "link": "https://tv.apple.com/us/movie/exodus/umc.cmc.43m6x8i0l0noq5r30cpkgukix",
          "price": "USD14.99"
        },
        {
          "service": "tubi",
          "type": "free",
          "quality": "hd",
          "link": "https://tubitv.com/movies/334153/exodus"
        },
        {
          "service": "prime",
          "type": "subscription",
          "quality": "sd",
          "link": "https://www.amazon.com/gp/video/detail/B07HS2VL8H/ref=atv_dp"
        },
        {
          "service": "prime",
          "type": "rent",
          "quality": "sd",
          "link": "https://www.amazon.com/gp/video/detail/B07HS2VL8H/ref=atv_dp",
          "price": "USD3.89"
        },
        {
          "service": "prime",
          "type": "buy",
          "quality": "sd",
          "link": "https://www.amazon.com/gp/video/detail/B07HS2VL8H/ref=atv_dp",
          "price": "USD12.99"
        }
      ]
    },
    {
      "episode_number": "151",
      "episode_url": "https://maximumfun.org/episodes/friendly-fire/in-the-army-now-1994/",
      "title": "The Sea Wolves",
      "year": "1980",
      "imdb_id": "tt0081470",
      "imdb_rating": "6.3",
      "imdb_votes": "5,507",
      "imdb_url": "https://www.imdb.com/title/tt0081470",
      "runtime": "120 min",
      "genre": "Action, History, War",
      "director": "Andrew V. McLaglen",
      "plot": "During World War II, British Intelligence brings a crew of ex-soldiers out of retirement, using their age as cover, to take to the seas and pull off an unlikely undercover mission in neutral Goa.",
      "poster": "https://m.media-amazon.com/images/M/MV5BYWEwN2QyNGQtZDE4Mi00MmFhLWI5OTUtNTJjMzhiNDJiMzMyXkEyXkFqcGc@._V1_SX300.jpg",
      "streaming_options": [
        {
          "service": "prime",
          "type": "buy",
          "quality": "sd",
          "link": "https://www.amazon.com/gp/video/detail/0NHEKISL4I2E5HCWZ6Q2TVQ1L4/ref=atv_dp",
          "price": "USD9.99"
        },
        {
          "service": "prime",
          "type": "rent",
          "quality": "sd",
          "link": "https://www.amazon.com/gp/video/detail/0NHEKISL4I2E5HCWZ6Q2TVQ1L4/ref=atv_dp",
          "price": "USD3.79"
        }
      ]
    },
    {
      "episode_number": "149",
      "episode_url": "https://maximumfun.org/episodes/friendly-fire/age-of-heroes-2011/",
      "title": "Dune",
      "year": "1984",
      "imdb_id": "tt0087182",
      "imdb_rating": "6.3",
      "imdb_votes": "191,067",
      "imdb_url": "https://www.imdb.com/title/tt0087182",
      "runtime": "137 min",
      "genre": "Action, Adventure, Sci-Fi",
      "director": "David Lynch",
      "plot": "A Duke's son leads desert warriors against the galactic emperor and his father's evil nemesis to free their desert world from the emperor's rule.",
      "poster": "https://m.media-amazon.com/images/M/MV5BMGJlMGM3NDAtOWNhMy00MWExLWI2MzEtMDQ0ZDIzZDY5ZmQ2XkEyXkFqcGc@._V1_SX300.jpg",
      "streaming_options": [
        {
          "service": "prime",
          "type": "rent",
          "quality": "hd",
          "link": "https://www.amazon.com/gp/video/detail/0P2VILG0ZV3399OWI3CSERZKL7/ref=atv_dp",
          "price": "USD3.79"
        },
        {
          "service": "prime",
          "type": "buy",
          "quality": "hd",
          "link": "https://www.amazon.com/gp/video/detail/0P2VILG0ZV3399OWI3CSERZKL7/ref=atv_dp",
          "price": "USD14.99"
        }
      ]
    },
    {
      "episode_number": "148",
      "episode_url": "https://maximumfun.org/episodes/friendly-fire/exodus-1960/",
      "title": "Jakob the Liar",
      "year": "1999",
      "imdb_id": "tt0120716",
      "imdb_rating": "6.5",
      "imdb_votes": "18,527",
      "imdb_url": "https://www.imdb.com/title/tt0120716",
      "runtime": "120 min",
      "genre": "Comedy, Drama, War",
      "director": "Peter Kassovitz",
      "plot": "During World War II, an ordinary inhabitant of a ghetto fakes news about Allied offensives to inspire hope for other victims of the Nazi regime.",
      "poster": "https://m.media-amazon.com/images/M/MV5BY2QyOTU2ZTAtYmRkMC00NDVjLThlNWQtMmI0MWI4NDM3YmRmXkEyXkFqcGc@._V1_SX300.jpg",
      "streaming_options": [
        {
          "service": "prime",
          "type": "buy",
          "quality": "hd",
          "link": "https://www.amazon.com/gp/video/detail/0T1QUG1BFXAALJ25D75U6JBMX9/ref=atv_dp",
          "price": "USD14.09"
        },
        {
          "service": "prime",
          "type": "buy",
          "quality": "sd",
          "link": "https://www.amazon.com/gp/video/detail/0T1QUG1BFXAALJ25D75U6JBMX9/ref=atv_dp",
          "price": "USD12.99"
        },
        {
          "service": "prime",
          "type": "rent",
          "quality": "hd",
          "link": "https://www.amazon.com/gp/video/detail/0T1QUG1BFXAALJ25D75U6JBMX9/ref=atv_dp",
          "price": "USD3.59"
        },
        {
          "service": "tubi",
          "type": "free",
          "quality": "hd",
          "link": "https://tubitv.com/movies/100039784/jakob-the-liar"
        }
      ]
    },
    {
      "episode_number": null,
      "episode_url": "https://maximumfun.org/boco/",
      "title": "Lone Survivor",
      "year": "2013",
      "imdb_id": "tt1091191",
      "imdb_rating": "7.5",
      "imdb_votes": "319,993",
      "imdb_url": "https://www.imdb.com/title/tt1091191",
      "runtime": "121 min",
      "genre": "Action, Biography, Drama",
      "director": "Peter Berg",
      "plot": "Marcus Luttrell and his team set out on a mission to capture or kill notorious Taliban leader Ahmad Shah, in late June 2005. Marcus and his team are left to fight for their lives in one of the most valiant efforts of modern warfare.",
      "poster": "https://m.media-amazon.com/images/M/MV5BMjA0NTgwOTk5Ml5BMl5BanBnXkFtZTcwMjE3NDc5OQ@@._V1_SX300.jpg",
      "streaming_options": [
        {
          "service": "prime",
          "type": "rent",
          "quality": "uhd",
          "link": "https://www.amazon.com/gp/video/detail/0FHW07P64EEBTUAKC060NSJAKY/ref=atv_dp",
          "price": "USD3.99"
        },
        {
          "service": "prime",
          "type": "buy",
          "quality": "uhd",
          "link": "https://www.amazon.com/gp/video/detail/0FHW07P64EEBTUAKC060NSJAKY/ref=atv_dp",
          "price": "USD14.99"
        }
      ]
    },
    {
      "episode_number": "147",
      "episode_url": "https://maximumfun.org/episodes/friendly-fire/the-sea-wolves-1980/",
      "title": "Path to War",
      "year": "2002",
      "imdb_id": "tt0218505",
      "imdb_rating": "7.3",
      "imdb_votes": "4,297",
      "imdb_url": "https://www.imdb.com/title/tt0218505",
      "runtime": "165 min",
      "genre": "Biography, Drama, War",
      "director": "John Frankenheimer",
      "plot": "In the mid 1960s, President Lyndon B. Johnson (Sir Michael Gambon) and his foreign-policy team debate the decision to withdraw from or escalate the war in Vietnam.",
      "poster": "https://m.media-amazon.com/images/M/MV5BN2RlZTYwMjMtOWI5NS00YTU3LWI0YzctYTdmOWIxOTMwMjljXkEyXkFqcGc@._V1_SX300.jpg",
      "streaming_options": [
        {
          "service": "hbo",
          "type": "subscription",
          "quality": "sd",
          "link": "https://play.hbomax.com/movie/e0657d07-9405-4408-9080-ec6c1041f7f3"
        },
        {
          "service": "prime",
          "type": "addon",
          "quality": "sd",
          "link": "https://www.amazon.com/gp/video/detail/0MOV1N3MT8ZEX39JTVOWKHDIB8/ref=atv_dp"
        },
        {
          "service": "prime",
          "type": "rent",
          "quality": "hd",
          "link": "https://www.amazon.com/gp/video/detail/0MOV1N3MT8ZEX39JTVOWKHDIB8/ref=atv_dp",
          "price": "USD3.79"
        },
        {
          "service": "prime",
          "type": "buy",
          "quality": "hd",
          "link": "https://www.amazon.com/gp/video/detail/0MOV1N3MT8ZEX39JTVOWKHDIB8/ref=atv_dp",
          "price": "USD9.99"
        },
        {
          "service": "prime",
          "type": "buy",
          "quality": "sd",
          "link": "https://www.amazon.com/gp/video/detail/0MOV1N3MT8ZEX39JTVOWKHDIB8/ref=atv_dp",
          "price": "USD7.99"
        }
      ]
    },
    {
      "episode_number": "146",
      "episode_url": "https://maximumfun.org/episodes/friendly-fire/the-secret-invasion-1964/",
      "title": "Mulan",
      "year": "1998",
      "imdb_id": "tt0120762",
      "imdb_rating": "7.7",
      "imdb_votes": "336,334",
      "imdb_url": "https://www.imdb.com/title/tt0120762",
      "runtime": "87 min",
      "genre": "Animation, Adventure, Comedy",
      "director": "Tony Bancroft, Barry Cook",
      "plot": "To save her father from death in the army, a young maiden secretly goes in his place and becomes one of China's greatest heroines in the process.",
      "poster": "https://m.media-amazon.com/images/M/MV5BYzU0ZTQxZDktOGY0Yy00NjdiLTllNDItMTMzMjI1YjMyYjRhXkEyXkFqcGc@._V1_SX300.jpg",
      "streaming_options": [
        {
          "service": "disney",
          "type": "subscription",
          "quality": "uhd",
          "link": "https://www.disneyplus.com/browse/entity-a89be7cf-d4a6-41e8-9e85-2040be26f401"
        },
        {
          "service": "prime",
          "type": "buy",
          "quality": "hd",
          "link": "https://www.amazon.com/gp/video/detail/0G9FXZRTWNADA0MX1RP3VMFRRQ/ref=atv_dp",
          "price": "USD19.99"
        }
      ]
    },
    {
      "episode_number": "145",
      "episode_url": "https://maximumfun.org/episodes/friendly-fire/the-devils-own-1997/",
      "title": "WarGames",
      "year": "1983",
      "imdb_id": "tt0086567",
      "imdb_rating": "7.1",
      "imdb_votes": "118,530",
      "imdb_url": "https://www.imdb.com/title/tt0086567",
      "runtime": "114 min",
      "genre": "Action, Drama, Sci-Fi",
      "director": "John Badham",
      "plot": "A young man finds a back door into a military central computer in which reality is confused with game-playing, possibly starting World War III.",
      "poster": "https://m.media-amazon.com/images/M/MV5BMmM5MDlmZWUtYTE1Mi00M2JiLTk1NzYtMTg0NTdlMzM2N2RkXkEyXkFqcGc@._V1_SX300.jpg",
      "streaming_options": [
        {
          "service": "apple",
          "type": "buy",
          "quality": "hd",
          "link": "https://tv.apple.com/us/movie/wargames/umc.cmc.4n8grrnb4vq7tgygwcd1cxzcq?playableId=tvs.sbd.9001%3A268643342",
          "price": "USD4.99"
        },
        {
          "service": "apple",
          "type": "rent",
          "quality": "hd",
          "link": "https://tv.apple.com/us/movie/wargames/umc.cmc.4n8grrnb4vq7tgygwcd1cxzcq?playableId=tvs.sbd.9001%3A268643342",
          "price": "USD3.99"
        },
        {
          "service": "tubi",
          "type": "free",
          "quality": "hd",
          "link": "https://tubitv.com/movies/604500/wargames"
        },
        {
          "service": "prime",
          "type": "subscription",
          "quality": "sd",
          "link": "https://www.amazon.com/gp/video/detail/0TVMXIGVWHESSW82W717FEO7DB/ref=atv_dp"
        },
        {
          "service": "prime",
          "type": "rent",
          "quality": "hd",
          "link": "https://www.amazon.com/gp/video/detail/0TVMXIGVWHESSW82W717FEO7DB/ref=atv_dp",
          "price": "USD3.89"
        },
        {
          "service": "prime",
          "type": "rent",
          "quality": "sd",
          "link": "https://www.amazon.com/gp/video/detail/0TVMXIGVWHESSW82W717FEO7DB/ref=atv_dp",
          "price": "USD2.99"
        },
        {
          "service": "prime",
          "type": "buy",
          "quality": "hd",
          "link": "https://www.amazon.com/gp/video/detail/0TVMXIGVWHESSW82W717FEO7DB/ref=atv_dp",
          "price": "USD14.99"
        },
        {
          "service": "plutotv",
          "type": "free",
          "quality": "sd",
          "link": "https://pluto.tv/gsa/on-demand/movies/5e3c8d1a86e96850bcc4a88f/details"
        }
      ]
    },
    {
      "episode_number": "144",
      "episode_url": "https://maximumfun.org/episodes/friendly-fire/thirteen-days-2000/",
      "title": "WarGames",
      "year": "1983",
      "imdb_id": "tt0086567",
      "imdb_rating": "7.1",
      "imdb_votes": "118,530",
      "imdb_url": "https://www.imdb.com/title/tt0086567",
      "runtime": "114 min",
      "genre": "Action, Drama, Sci-Fi",
      "director": "John Badham",
      "plot": "A young man finds a back door into a military central computer in which reality is confused with game-playing, possibly starting World War III.",
      "poster": "https://m.media-amazon.com/images/M/MV5BMmM5MDlmZWUtYTE1Mi00M2JiLTk1NzYtMTg0NTdlMzM2N2RkXkEyXkFqcGc@._V1_SX300.jpg",
      "streaming_options": [
        {
          "service": "apple",
          "type": "buy",
          "quality": "hd",
          "link": "https://tv.apple.com/us/movie/wargames/umc.cmc.4n8grrnb4vq7tgygwcd1cxzcq?playableId=tvs.sbd.9001%3A268643342",
          "price": "USD4.99"
        },
        {
          "service": "apple",
          "type": "rent",
          "quality": "hd",
          "link": "https://tv.apple.com/us/movie/wargames/umc.cmc.4n8grrnb4vq7tgygwcd1cxzcq?playableId=tvs.sbd.9001%3A268643342",
          "price": "USD3.99"
        },
        {
          "service": "tubi",
          "type": "free",
          "quality": "hd",
          "link": "https://tubitv.com/movies/604500/wargames"
        },
        {
          "service": "prime",
          "type": "subscription",
          "quality": "sd",
          "link": "https://www.amazon.com/gp/video/detail/0TVMXIGVWHESSW82W717FEO7DB/ref=atv_dp"
        },
        {
          "service": "prime",
          "type": "rent",
          "quality": "hd",
          "link": "https://www.amazon.com/gp/video/detail/0TVMXIGVWHESSW82W717FEO7DB/ref=atv_dp",
          "price": "USD3.89"
        },
        {
          "service": "prime",
          "type": "rent",
          "quality": "sd",
          "link": "https://www.amazon.com/gp/video/detail/0TVMXIGVWHESSW82W717FEO7DB/ref=atv_dp",
          "price": "USD2.99"
        },
        {
          "service": "prime",
          "type": "buy",
          "quality": "hd",
          "link": "https://www.amazon.com/gp/video/detail/0TVMXIGVWHESSW82W717FEO7DB/ref=atv_dp",
          "price": "USD14.99"
        },
        {
          "service": "plutotv",
          "type": "free",
          "quality": "sd",
          "link": "https://pluto.tv/gsa/on-demand/movies/5e3c8d1a86e96850bcc4a88f/details"
        }
      ]
    },
    {
      "episode_number": null,
      "episode_url": "https://maximumfun.org/boco/",
      "title": "WarGames",
      "year": "1983",
      "imdb_id": "tt0086567",
      "imdb_rating": "7.1",
      "imdb_votes": "118,530",
      "imdb_url": "https://www.imdb.com/title/tt0086567",
      "runtime": "114 min",
      "genre": "Action, Drama, Sci-Fi",
      "director": "John Badham",
      "plot": "A young man finds a back door into a military central computer in which reality is confused with game-playing, possibly starting World War III.",
      "poster": "https://m.media-amazon.com/images/M/MV5BMmM5MDlmZWUtYTE1Mi00M2JiLTk1NzYtMTg0NTdlMzM2N2RkXkEyXkFqcGc@._V1_SX300.jpg",
      "streaming_options": [
        {
          "service": "apple",
          "type": "buy",
          "quality": "hd",
          "link": "https://tv.apple.com/us/movie/wargames/umc.cmc.4n8grrnb4vq7tgygwcd1cxzcq?playableId=tvs.sbd.9001%3A268643342",
          "price": "USD4.99"
        },
        {
          "service": "apple",
          "type": "rent",
          "quality": "hd",
          "link": "https://tv.apple.com/us/movie/wargames/umc.cmc.4n8grrnb4vq7tgygwcd1cxzcq?playableId=tvs.sbd.9001%3A268643342",
          "price": "USD3.99"
        },
        {
          "service": "tubi",
          "type": "free",
          "quality": "hd",
          "link": "https://tubitv.com/movies/604500/wargames"
        },
        {
          "service": "prime",
          "type": "subscription",
          "quality": "sd",
          "link": "https://www.amazon.com/gp/video/detail/0TVMXIGVWHESSW82W717FEO7DB/ref=atv_dp"
        },
        {
          "service": "prime",
          "type": "rent",
          "quality": "hd",
          "link": "https://www.amazon.com/gp/video/detail/0TVMXIGVWHESSW82W717FEO7DB/ref=atv_dp",
          "price": "USD3.89"
        },
        {
          "service": "prime",
          "type": "rent",
          "quality": "sd",
          "link": "https://www.amazon.com/gp/video/detail/0TVMXIGVWHESSW82W717FEO7DB/ref=atv_dp",
          "price": "USD2.99"
        },
        {
          "service": "prime",
          "type": "buy",
          "quality": "hd",
          "link": "https://www.amazon.com/gp/video/detail/0TVMXIGVWHESSW82W717FEO7DB/ref=atv_dp",
          "price": "USD14.99"
        },
        {
          "service": "plutotv",
          "type": "free",
          "quality": "sd",
          "link": "https://pluto.tv/gsa/on-demand/movies/5e3c8d1a86e96850bcc4a88f/details"
        }
      ]
    },
    {
      "episode_number": "143",
      "episode_url": "https://maximumfun.org/episodes/friendly-fire/flight-of-the-intruder-1991/",
      "title": "Good Kill",
      "year": "2014",
      "imdb_id": "tt3297330",
      "imdb_rating": "6.4",
      "imdb_votes": "25,545",
      "imdb_url": "https://www.imdb.com/title/tt3297330",
      "runtime": "102 min",
      "genre": "Drama, Thriller, War",
      "director": "Andrew Niccol",
      "plot": "A family man begins to question the ethics of his job as a drone pilot.",
      "poster": "https://m.media-amazon.com/images/M/MV5BMTkzNDIxNzE5OF5BMl5BanBnXkFtZTgwODMxMTExNTE@._V1_SX300.jpg",
      "streaming_options": [
        {
          "service": "prime",
          "type": "addon",
          "quality": "sd",
          "link": "https://www.amazon.com/gp/video/detail/B00KNOVKNE/ref=atv_dp"
        },
        {
          "service": "prime",
          "type": "buy",
          "quality": "sd",
          "link": "https://www.amazon.com/gp/video/detail/B00KNOVKNE/ref=atv_dp",
          "price": "USD9.99"
        },
        {
          "service": "apple",
          "type": "addon",
          "quality": "hd",
          "link": "https://tv.apple.com/us/movie/good-kill/umc.cmc.hs8ae6zbp9eixalisb9qy0k9"
        },
        {
          "service": "apple",
          "type": "addon",
          "quality": "hd",
          "link": "https://tv.apple.com/us/movie/good-kill/umc.cmc.hs8ae6zbp9eixalisb9qy0k9"
        },
        {
          "service": "apple",
          "type": "buy",
          "quality": "hd",
          "link": "https://tv.apple.com/us/movie/good-kill/umc.cmc.hs8ae6zbp9eixalisb9qy0k9",
          "price": "USD12.99"
        },
        {
          "service": "apple",
          "type": "rent",
          "quality": "hd",
          "link": "https://tv.apple.com/us/movie/good-kill/umc.cmc.hs8ae6zbp9eixalisb9qy0k9",
          "price": "USD3.99"
        },
        {
          "service": "prime",
          "type": "addon",
          "quality": "sd",
          "link": "https://www.amazon.com/gp/video/detail/B00KNOVKNE/ref=atv_dp"
        },
        {
          "service": "prime",
          "type": "buy",
          "quality": "hd",
          "link": "https://www.amazon.com/gp/video/detail/B00KNOVKNE/ref=atv_dp",
          "price": "USD11.09"
        },
        {
          "service": "prime",
          "type": "addon",
          "quality": "sd",
          "link": "https://www.amazon.com/gp/video/detail/0L45IM9GV8MALXJGUE25F18NN9/ref=atv_dp"
        },
        {
          "service": "prime",
          "type": "addon",
          "quality": "sd",
          "link": "https://www.amazon.com/gp/video/detail/0L45IM9GV8MALXJGUE25F18NN9/ref=atv_dp"
        },
        {
          "service": "prime",
          "type": "addon",
          "quality": "sd",
          "link": "https://www.amazon.com/gp/video/detail/0L45IM9GV8MALXJGUE25F18NN9/ref=atv_dp"
        },
        {
          "service": "tubi",
          "type": "free",
          "quality": "hd",
          "link": "https://tubitv.com/movies/676670/good-kill"
        },
        {
          "service": "hulu",
          "type": "addon",
          "quality": "hd",
          "link": "https://www.hulu.com/movie/good-kill-89da33ae-c83f-42a0-9192-65f7dd73796d"
        },
        {
          "service": "paramount",
          "type": "addon",
          "quality": "sd",
          "link": "https://www.paramountplus.com/movies/video/q0FlJkua1PZKODr5xwfIJDdvPxVHNitd/"
        },
        {
          "service": "plutotv",
          "type": "free",
          "quality": "sd",
          "link": "https://pluto.tv/gsa/on-demand/movies/636c2cc5bc198f001337fd4d/details"
        }
      ]
    },
    {
      "episode_number": "142",
      "episode_url": "https://maximumfun.org/episodes/friendly-fire/jakob-the-liar-1999/",
      "title": "In Which We Serve",
      "year": "1942",
      "imdb_id": "tt0034891",
      "imdb_rating": "7.2",
      "imdb_votes": "6,880",
      "imdb_url": "https://www.imdb.com/title/tt0034891",
      "runtime": "115 min",
      "genre": "Drama, War",
      "director": "Noël Coward, David Lean",
      "plot": "This \"story of a ship\", the British destroyer H.M.S. Torrin, is told in flashbacks by survivors as they cling to a life raft.",
      "poster": "https://m.media-amazon.com/images/M/MV5BMjE3MTJkOWUtMDMwNy00MWU5LWFjZjctZTI4MTlmZGJkMzU1XkEyXkFqcGc@._V1_SX300.jpg",
      "streaming_options": [
        {
          "service": "apple",
          "type": "buy",
          "quality": "hd",
          "link": "https://tv.apple.com/us/movie/in-which-we-serve/umc.cmc.2mgdnywtqpaus9kadh9n8axir",
          "price": "USD14.99"
        },
        {
          "service": "apple",
          "type": "rent",
          "quality": "hd",
          "link": "https://tv.apple.com/us/movie/in-which-we-serve/umc.cmc.2mgdnywtqpaus9kadh9n8axir",
          "price": "USD3.99"
        },
        {
          "service": "prime",
          "type": "rent",
          "quality": "sd",
          "link": "https://www.amazon.com/gp/video/detail/0HBR13XWG2MZVF0IJ958S6XOTN/ref=atv_dp",
          "price": "USD0.99"
        },
        {
          "service": "prime",
          "type": "buy",
          "quality": "sd",
          "link": "https://www.amazon.com/gp/video/detail/0HBR13XWG2MZVF0IJ958S6XOTN/ref=atv_dp",
          "price": "USD2.99"
        },
        {
          "service": "tubi",
          "type": "free",
          "quality": "hd",
          "link": "https://tubitv.com/movies/100004549/in-which-we-serve"
        },
        {
          "service": "hulu",
          "type": "addon",
          "quality": "hd",
          "link": "https://www.hulu.com/movie/in-which-we-serve-07dc95a2-9e09-4b4b-9d9a-7e6e3f427fab"
        },
        {
          "service": "hbo",
          "type": "subscription",
          "quality": "sd",
          "link": "https://play.hbomax.com/movie/60e6fe10-395f-44fa-95a8-2b77cccb19c9"
        },
        {
          "service": "prime",
          "type": "addon",
          "quality": "sd",
          "link": "https://www.amazon.com/gp/video/detail/0JNW2HN3GZTNJXLNFASVP9NTVM/ref=atv_dp"
        },
        {
          "service": "prime",
          "type": "rent",
          "quality": "hd",
          "link": "https://www.amazon.com/gp/video/detail/0JNW2HN3GZTNJXLNFASVP9NTVM/ref=atv_dp",
          "price": "USD3.99"
        },
        {
          "service": "prime",
          "type": "buy",
          "quality": "hd",
          "link": "https://www.amazon.com/gp/video/detail/0JNW2HN3GZTNJXLNFASVP9NTVM/ref=atv_dp",
          "price": "USD19.99"
        }
      ]
    },
    {
      "episode_number": "140",
      "episode_url": "https://maximumfun.org/episodes/friendly-fire/dead-presidents-1995/",
      "title": "Operation Pacific",
      "year": "1951",
      "imdb_id": "tt0043887",
      "imdb_rating": "6.6",
      "imdb_votes": "4,038",
      "imdb_url": "https://www.imdb.com/title/tt0043887",
      "runtime": "111 min",
      "genre": "Drama, Romance, War",
      "director": "George Waggner",
      "plot": "During WWII, a submarine's second in command inherits the problem of torpedoes that don't explode. When on shore, he is eager to win back his ex-wife.",
      "poster": "https://m.media-amazon.com/images/M/MV5BYTI1M2FjYjQtY2NkZS00OTQ1LTg1ZjUtZDRkOTI4MTVmOWM4XkEyXkFqcGc@._V1_SX300.jpg",
      "streaming_options": [
        {
          "service": "prime",
          "type": "rent",
          "quality": "hd",
          "link": "https://www.amazon.com/gp/video/detail/0J3QEEAJZO6VD3CP5HOO7504UJ/ref=atv_dp",
          "price": "USD3.79"
        },
        {
          "service": "prime",
          "type": "buy",
          "quality": "hd",
          "link": "https://www.amazon.com/gp/video/detail/0J3QEEAJZO6VD3CP5HOO7504UJ/ref=atv_dp",
          "price": "USD9.99"
        }
      ]
    },
    {
      "episode_number": "137",
      "episode_url": "https://maximumfun.org/episodes/friendly-fire/greyhound-2020/",
      "title": "Patriot Games",
      "year": "1992",
      "imdb_id": "tt0105112",
      "imdb_rating": "6.8",
      "imdb_votes": "126,564",
      "imdb_url": "https://www.imdb.com/title/tt0105112",
      "runtime": "117 min",
      "genre": "Action, Thriller",
      "director": "Phillip Noyce",
      "plot": "When CIA analyst Jack Ryan interferes with an IRA assassination, a renegade faction targets him and his family for revenge.",
      "poster": "https://m.media-amazon.com/images/M/MV5BZWQ3Y2NiOGEtNjdmMS00ODI1LTk0ODktM2U3NjllNzlmZTkxXkEyXkFqcGc@._V1_SX300.jpg",
      "streaming_options": [
        {
          "service": "hulu",
          "type": "addon",
          "quality": "hd",
          "link": "https://www.hulu.com/movie/patriot-games-3a75b5d5-0b14-4aa0-bc3d-a5cf4cb9d95d"
        },
        {
          "service": "prime",
          "type": "addon",
          "quality": "uhd",
          "link": "https://www.amazon.com/gp/video/detail/0HSSUB0YOI71175VZTRZUEYBLX/ref=atv_dp"
        },
        {
          "service": "prime",
          "type": "rent",
          "quality": "uhd",
          "link": "https://www.amazon.com/gp/video/detail/0HSSUB0YOI71175VZTRZUEYBLX/ref=atv_dp",
          "price": "USD3.79"
        },
        {
          "service": "prime",
          "type": "buy",
          "quality": "uhd",
          "link": "https://www.amazon.com/gp/video/detail/0HSSUB0YOI71175VZTRZUEYBLX/ref=atv_dp",
          "price": "USD14.99"
        },
        {
          "service": "plutotv",
          "type": "free",
          "quality": "sd",
          "link": "https://pluto.tv/gsa/on-demand/movies/5bd3337867f34cef7af44774/details"
        }
      ]
    },
    {
      "episode_number": null,
      "episode_url": "https://maximumfun.org/boco/",
      "title": "War of the Worlds",
      "year": "2005",
      "imdb_id": "tt0407304",
      "imdb_rating": "6.6",
      "imdb_votes": "500,526",
      "imdb_url": "https://www.imdb.com/title/tt0407304",
      "runtime": "117 min",
      "genre": "Action, Adventure, Sci-Fi",
      "director": "Steven Spielberg",
      "plot": "An alien invasion threatens the future of humanity. The catastrophic nightmare is depicted through the eyes of one American family fighting for survival.",
      "poster": "https://m.media-amazon.com/images/M/MV5BNDUyODAzNDI1Nl5BMl5BanBnXkFtZTcwMDA2NDAzMw@@._V1_SX300.jpg",
      "streaming_options": [
        {
          "service": "tubi",
          "type": "free",
          "quality": "sd",
          "link": "https://tubitv.com/movies/576134/war-of-the-worlds"
        },
        {
          "service": "paramount",
          "type": "subscription",
          "quality": "sd",
          "link": "https://www.paramountplus.com/movies/video/6EBZOegEKE2E4svmjhQ4kIBNRI9y8eTq/"
        },
        {
          "service": "plutotv",
          "type": "free",
          "quality": "sd",
          "link": "https://pluto.tv/gsa/on-demand/movies/625ef985025eb50013a4cb42/details"
        }
      ]
    },
    {
      "episode_number": null,
      "episode_url": "https://maximumfun.org/episodes/friendly-fire/ep-124-the-night-of-the-generals-1967/",
      "title": "Lord of War",
      "year": "2005",
      "imdb_id": "tt0399295",
      "imdb_rating": "7.6",
      "imdb_votes": "353,357",
      "imdb_url": "https://www.imdb.com/title/tt0399295",
      "runtime": "122 min",
      "genre": "Crime, Drama",
      "director": "Andrew Niccol",
      "plot": "An arms dealer confronts the morality of his work as he is being chased by an INTERPOL Agent.",
      "poster": "https://m.media-amazon.com/images/M/MV5BNThlY2NkYmMtNTFhNi00MzBiLWJmNzEtZjk5MzYwYWU2MjllXkEyXkFqcGc@._V1_SX300.jpg",
      "streaming_options": [
        {
          "service": "apple",
          "type": "rent",
          "quality": "hd",
          "link": "https://tv.apple.com/us/movie/lord-of-war/umc.cmc.33c8emvylqpid7l1uf71orhz4?playableId=tvs.sbd.9001%3A256152991",
          "price": "USD3.99"
        },
        {
          "service": "apple",
          "type": "buy",
          "quality": "hd",
          "link": "https://tv.apple.com/us/movie/lord-of-war/umc.cmc.33c8emvylqpid7l1uf71orhz4?playableId=tvs.sbd.9001%3A256152991",
          "price": "USD4.99"
        },
        {
          "service": "prime",
          "type": "subscription",
          "quality": "uhd",
          "link": "https://www.amazon.com/gp/video/detail/0RC63K6M3LSBYO1EHHX2H6A7S6/ref=atv_dp"
        },
        {
          "service": "prime",
          "type": "addon",
          "quality": "uhd",
          "link": "https://www.amazon.com/gp/video/detail/0RC63K6M3LSBYO1EHHX2H6A7S6/ref=atv_dp"
        },
        {
          "service": "prime",
          "type": "addon",
          "quality": "uhd",
          "link": "https://www.amazon.com/gp/video/detail/0RC63K6M3LSBYO1EHHX2H6A7S6/ref=atv_dp"
        },
        {
          "service": "prime",
          "type": "buy",
          "quality": "uhd",
          "link": "https://www.amazon.com/gp/video/detail/0RC63K6M3LSBYO1EHHX2H6A7S6/ref=atv_dp",
          "price": "USD4.99"
        },
        {
          "service": "prime",
          "type": "rent",
          "quality": "uhd",
          "link": "https://www.amazon.com/gp/video/detail/0RC63K6M3LSBYO1EHHX2H6A7S6/ref=atv_dp",
          "price": "USD3.79"
        },
        {
          "service": "plutotv",
          "type": "free",
          "quality": "sd",
          "link": "https://pluto.tv/gsa/on-demand/movies/5a591b472aee82cc6ec114f7/details"
        }
      ]
    }
  ]
}